galaxy2janis/__init__.py
galaxy2janis/aliases.py
galaxy2janis/cli.py
galaxy2janis/ingest.py
galaxy2janis/run.py
galaxy2janis/containers/Container.py
galaxy2janis/containers/ContainerCache.py
galaxy2janis/containers/__init__.py
galaxy2janis/containers/fetch.py
galaxy2janis/containers/fetching/ContainerReqFetcher.py
galaxy2janis/containers/fetching/Fetcher.py
galaxy2janis/containers/fetching/GA4GHFetcher.py
galaxy2janis/containers/fetching/QuayIOFetcher.py
galaxy2janis/containers/fetching/__init__.py
galaxy2janis/containers/fetching/presets.py
galaxy2janis/containers/fetching/utils.py
galaxy2janis/containers/selection/VersionMatcher.py
galaxy2janis/containers/selection/__init__.py
galaxy2janis/containers/selection/selection.py
galaxy2janis/data/container_url_cache.json
galaxy2janis/data/galaxy_config.yaml
galaxy2janis/data/galaxy_janis_types.yaml
galaxy2janis/data/logging_config.yaml
galaxy2janis/data/wrappers.json
galaxy2janis/datatypes/JanisDatatype.py
galaxy2janis/datatypes/__init__.py
galaxy2janis/datatypes/conversion.py
galaxy2janis/datatypes/core.py
galaxy2janis/datatypes/galaxy.py
galaxy2janis/datatypes/main.py
galaxy2janis/datatypes/register.py
galaxy2janis/datatypes/strategies.py
galaxy2janis/entities/__init__.py
galaxy2janis/entities/protocols.py
galaxy2janis/entities/tool/Tool.py
galaxy2janis/entities/tool/ToolFactory.py
galaxy2janis/entities/tool/__init__.py
galaxy2janis/entities/tool/generate.py
galaxy2janis/entities/tool/outputs.py
galaxy2janis/entities/workflow/__init__.py
galaxy2janis/entities/workflow/input.py
galaxy2janis/entities/workflow/metadata.py
galaxy2janis/entities/workflow/workflow.py
galaxy2janis/entities/workflow/registers/StepInputRegister.py
galaxy2janis/entities/workflow/registers/StepOutputRegister.py
galaxy2janis/entities/workflow/registers/__init__.py
galaxy2janis/entities/workflow/step/__init__.py
galaxy2janis/entities/workflow/step/inputs.py
galaxy2janis/entities/workflow/step/metadata.py
galaxy2janis-0.1.2.dist-info/LICENCE.txt
galaxy2janis-0.1.2.dist-info/METADATA
galaxy2janis-0.1.2.dist-info/WHEEL
galaxy2janis-0.1.2.dist-info/entry_points.txt
galaxy2janis-0.1.2.dist-info/top_level.txt
galaxy2janis-0.1.2.dist-info/RECORD
