Metadata-Version: 2.1
Name: galaxy2janis
Version: 0.1.2
Summary: ingestion of galaxy tool wrappers (.xml) and workflows (.ga) into the janis language.
Home-page: UNKNOWN
Author: Grace Hall
License: MIT
Platform: UNKNOWN
License-File: LICENCE.txt
Requires-Dist: galaxy-app (==22.1.1)
Requires-Dist: janis-pipelines (==0.11.6)
Requires-Dist: biopython (==1.79)
Requires-Dist: filelock (==3.7.0)
